{"response":0,"message":"","data":{"data":[{"id":22661,"uid":21937,"user":"\u8fea\u9a6c","credit":"204.9","equity":"2164.08\u4e07","total_nav":"2.1553","max_lost":"6.04%","tn_profit":12171591.14,"total_yield":"<em style=\"font-style:normal;color:#ff287e\">115.53%<\/em>","avg_equity":"1500.28\u4e07","first_date":"2025-07-01","dateline":"2026-02-25","no":1,"company":"\u65b9\u6b63\u4e2d\u671f"},{"id":27171,"uid":21463,"user":"chenq1","credit":"202.5","equity":"1943.76\u4e07","total_nav":"3.9769","max_lost":"14.58%","tn_profit":14770622.440000001,"total_yield":"<em style=\"font-style:normal;color:#ff287e\">297.69%<\/em>","avg_equity":"1252.59\u4e07","first_date":"2025-07-01","dateline":"2026-02-25","no":2,"company":"\u4fe1\u8fbe\u671f\u8d27"},{"id":26731,"uid":21463,"user":"\u5c0f\u7b28\u4e13\u6237\u4e00\u53f7","credit":"198.9","equity":"3710.75\u4e07","total_nav":"2.7668","max_lost":"12.29%","tn_profit":14800571.689999996,"total_yield":"<em style=\"font-style:normal;color:#ff287e\">176.68%<\/em>","avg_equity":"1575.89\u4e07","first_date":"2025-07-01","dateline":"2026-02-25","no":3,"company":"\u4e1c\u822a\u671f\u8d27"},{"id":24560,"uid":23398,"user":"liwenyan\u4e94\u77ff","credit":"193.9","equity":"1.01\u4ebf","total_nav":"4.2481","max_lost":"18.45%","tn_profit":153418547.79000002,"total_yield":"<em style=\"font-style:normal;color:#ff287e\">324.81%<\/em>","avg_equity":"1.28\u4ebf","first_date":"2025-07-01","dateline":"2026-02-25","no":4,"company":"\u4e94\u77ff\u671f\u8d27"},{"id":16879,"uid":16879,"user":"\u5357\u534eJM","credit":"192.8","equity":"134.83\u4e07","total_nav":"3.5969","max_lost":"5.94%","tn_profit":1111611.6900000006,"total_yield":"<em style=\"font-style:normal;color:#ff287e\">259.69%<\/em>","avg_equity":"84.44\u4e07","first_date":"2025-07-01","dateline":"2026-02-25","no":5,"company":"\u5357\u534e\u671f\u8d27"},{"id":10231,"uid":10231,"user":"\u5fc3\u7075\u57fa\u91d1","credit":"192.5","equity":"1102.15\u4e07","total_nav":"1.8556","max_lost":"6.51%","tn_profit":5412699.63,"total_yield":"<em style=\"font-style:normal;color:#ff287e\">85.56%<\/em>","avg_equity":"796.46\u4e07","first_date":"2025-07-01","dateline":"2026-02-25","no":6,"company":"\u4e1c\u822a\u671f\u8d27"},{"id":21152,"uid":23398,"user":"\u957f\u91cf\u7231\u98de1\u53f7","credit":"192.4","equity":"7251.21\u4e07","total_nav":"3.4947","max_lost":"17.33%","tn_profit":41079066.10000002,"total_yield":"<em style=\"font-style:normal;color:#ff287e\">249.47%<\/em>","avg_equity":"3743.03\u4e07","first_date":"2025-07-01","dateline":"2026-02-25","no":7,"company":"\u534e\u6cf0\u671f\u8d27"},{"id":22084,"uid":21845,"user":"\u7384\u94c1\u91cd\u5251","credit":"191.0","equity":"2404.43\u4e07","total_nav":"1.6899","max_lost":"5.50%","tn_profit":7141643.370000004,"total_yield":"<em style=\"font-style:normal;color:#ff287e\">68.99%<\/em>","avg_equity":"1499.02\u4e07","first_date":"2025-07-01","dateline":"2026-02-25","no":8,"company":"\u56fd\u6295\u5b89\u4fe1"},{"id":26466,"uid":21931,"user":"\u4f20\u5947\u5730\u9009\u738b2\u53f7","credit":"188.4","equity":"552.95\u4e07","total_nav":"2.1902","max_lost":"9.34%","tn_profit":2902797.480000001,"total_yield":"<em style=\"font-style:normal;color:#ff287e\">119.02%<\/em>","avg_equity":"395.91\u4e07","first_date":"2025-07-01","dateline":"2026-02-25","no":9,"company":"\u5149\u5927\u671f\u8d27"},{"id":11795,"uid":23277,"user":"\u8054\u5510\u4e00\u53f7","credit":"186.9","equity":"373.08\u4e07","total_nav":"2.6106","max_lost":"12.85%","tn_profit":3945873.8299999973,"total_yield":"<em style=\"font-style:normal;color:#ff287e\">161.06%<\/em>","avg_equity":"364.25\u4e07","first_date":"2025-07-01","dateline":"2026-02-25","no":10,"company":"\u56fd\u4fe1\u671f\u8d27"},{"id":7270,"uid":7270,"user":"\u987a\u8f7b\u6b62","credit":"186.4","equity":"1.98\u4e07","total_nav":"4.1483","max_lost":"3.49%","tn_profit":30201,"total_yield":"<em style=\"font-style:normal;color:#ff287e\">314.83%<\/em>","avg_equity":"1.65\u4e07","first_date":"2025-07-01","dateline":"2026-02-25","no":11,"company":"\u7533\u94f6\u4e07\u56fd"},{"id":24562,"uid":6811,"user":"\u8042\u6210\u4e94\u77ff","credit":"186.2","equity":"1819.85\u4e07","total_nav":"2.2811","max_lost":"14.21%","tn_profit":10679120.87,"total_yield":"<em style=\"font-style:normal;color:#ff287e\">128.11%<\/em>","avg_equity":"1308.84\u4e07","first_date":"2025-07-01","dateline":"2026-02-25","no":12,"company":"\u4e94\u77ff\u671f\u8d27"},{"id":25009,"uid":23657,"user":"\u914b\u957f\u5728\u8def\u4e0a","credit":"185.8","equity":"1622.87\u4e07","total_nav":"4.0850","max_lost":"19.32%","tn_profit":15093298.94,"total_yield":"<em style=\"font-style:normal;color:#ff287e\">308.50%<\/em>","avg_equity":"1117.34\u4e07","first_date":"2025-07-01","dateline":"2026-02-25","no":13,"company":"\u6c11\u751f\u671f\u8d27"},{"id":7915,"uid":7915,"user":"hehai0344","credit":"184.8","equity":"352.96\u4e07","total_nav":"3.2436","max_lost":"13.92%","tn_profit":2603526.6299999994,"total_yield":"<em style=\"font-style:normal;color:#ff287e\">224.36%<\/em>","avg_equity":"190.05\u4e07","first_date":"2025-07-01","dateline":"2026-02-25","no":14,"company":"\u4e1c\u534e\u671f\u8d27"},{"id":13924,"uid":23758,"user":"\u4ef7\u503c\u822a\u6807","credit":"183.8","equity":"3844.37\u4e07","total_nav":"1.6357","max_lost":"8.15%","tn_profit":14943063.269999992,"total_yield":"<em style=\"font-style:normal;color:#ff287e\">63.57%<\/em>","avg_equity":"3552.03\u4e07","first_date":"2025-07-01","dateline":"2026-02-25","no":15,"company":"\u56fd\u91d1\u671f\u8d27"},{"id":26914,"uid":18745,"user":"\u8fc7\u6cb3\u5352","credit":"181.2","equity":"193.85\u4e07","total_nav":"5.6974","max_lost":"15.36%","tn_profit":2297976.809999999,"total_yield":"<em style=\"font-style:normal;color:#ff287e\">469.74%<\/em>","avg_equity":"118.88\u4e07","first_date":"2025-07-01","dateline":"2026-02-25","no":16,"company":"\u5b9d\u57ce\u671f\u8d27"},{"id":26388,"uid":20406,"user":"\u5168\u519b\u51fa\u51fb","credit":"180.9","equity":"1.49\u4ebf","total_nav":"2.6677","max_lost":"18.65%","tn_profit":151763330.74999997,"total_yield":"<em style=\"font-style:normal;color:#ff287e\">166.77%<\/em>","avg_equity":"1.61\u4ebf","first_date":"2025-07-01","dateline":"2025-12-31","no":17,"company":"\u6c38\u5b89\u671f\u8d27"},{"id":6993,"uid":24360,"user":"\u5927\u6d77\u7684\u65b9\u5411","credit":"179.9","equity":"731.72\u4e07","total_nav":"2.3217","max_lost":"15.07%","tn_profit":4321587.69,"total_yield":"<em style=\"font-style:normal;color:#ff287e\">132.17%<\/em>","avg_equity":"551.26\u4e07","first_date":"2025-07-01","dateline":"2026-02-25","no":18,"company":"\u65b9\u6b63\u4e2d\u671f"},{"id":26750,"uid":24425,"user":"\u9ebb\u8fa3\u738b\u5b502","credit":"179.1","equity":"456.18\u4e07","total_nav":"1.9942","max_lost":"10.58%","tn_profit":2318963.5400000024,"total_yield":"<em style=\"font-style:normal;color:#ff287e\">99.42%<\/em>","avg_equity":"374.48\u4e07","first_date":"2025-07-01","dateline":"2026-02-25","no":19,"company":"\u5149\u5927\u671f\u8d27"},{"id":26072,"uid":24268,"user":"\u6656\u6708\u8d44\u7ba1","credit":"177.3","equity":"810.31\u4e07","total_nav":"2.5080","max_lost":"16.28%","tn_profit":5440798.3999999985,"total_yield":"<em style=\"font-style:normal;color:#ff287e\">150.80%<\/em>","avg_equity":"449.81\u4e07","first_date":"2025-07-01","dateline":"2026-02-25","no":20,"company":"\u534e\u6cf0\u671f\u8d27"},{"id":11171,"uid":11171,"user":"\u7384\u6b66\u76db\u548cCTA\u58f9\u53f7","credit":"177.2","equity":"306.49\u4e07","total_nav":"2.1592","max_lost":"11.71%","tn_profit":2020601.6500000006,"total_yield":"<em style=\"font-style:normal;color:#ff287e\">115.92%<\/em>","avg_equity":"242.12\u4e07","first_date":"2025-07-01","dateline":"2026-02-25","no":21,"company":"\u6d77\u901a\u671f\u8d27"},{"id":25416,"uid":23895,"user":"\u731b\u864e\u4f20\u8bf4","credit":"176.9","equity":"1298.23\u4e07","total_nav":"2.6803","max_lost":"16.89%","tn_profit":7964043.029999999,"total_yield":"<em style=\"font-style:normal;color:#ff287e\">168.03%<\/em>","avg_equity":"459.22\u4e07","first_date":"2025-07-01","dateline":"2026-02-25","no":22,"company":"\u6d77\u8bc1\u671f\u8d27"},{"id":25394,"uid":23886,"user":"\u6c47\u667a\u878d\u8fbe-\u96f6\u82b1\u94b12\u53f7","credit":"175.1","equity":"100.00\u4e07","total_nav":"3.5214","max_lost":"16.83%","tn_profit":2203202.4199999995,"total_yield":"<em style=\"font-style:normal;color:#ff287e\">252.14%<\/em>","avg_equity":"174.07\u4e07","first_date":"2025-07-01","dateline":"2026-02-25","no":23,"company":"\u51a0\u901a\u671f\u8d27"},{"id":23988,"uid":9150,"user":"\u5434\u4e49\u9e4f008","credit":"174.9","equity":"173.71\u4e07","total_nav":"2.3618","max_lost":"11.21%","tn_profit":1203407.2099999986,"total_yield":"<em style=\"font-style:normal;color:#ff287e\">136.18%<\/em>","avg_equity":"131.39\u4e07","first_date":"2025-07-01","dateline":"2026-02-25","no":24,"company":"\u4e1c\u8bc1\u671f\u8d27"},{"id":7124,"uid":7124,"user":"\u81ea\u5a31\u81ea\u4e50","credit":"174.5","equity":"121.22\u4e07","total_nav":"4.7972","max_lost":"14.44%","tn_profit":1442421.1800000002,"total_yield":"<em style=\"font-style:normal;color:#ff287e\">379.72%<\/em>","avg_equity":"81.29\u4e07","first_date":"2025-07-01","dateline":"2026-02-25","no":25,"company":"\u4e0a\u6d77\u4e2d\u671f"},{"id":27074,"uid":24705,"user":"\u98de\u54e5","credit":"174.2","equity":"219.85","total_nav":"2.0513","max_lost":"8.73%","tn_profit":2243961.240000001,"total_yield":"<em style=\"font-style:normal;color:#ff287e\">105.13%<\/em>","avg_equity":"138.92\u4e07","first_date":"2025-07-01","dateline":"2026-02-25","no":26,"company":"\u4e1c\u5434\u671f\u8d27"},{"id":21291,"uid":23398,"user":"\u674e\u6587\u8273","credit":"174.2","equity":"633.08\u4e07","total_nav":"1.6321","max_lost":"10.11%","tn_profit":6445788.129999998,"total_yield":"<em style=\"font-style:normal;color:#ff287e\">63.21%<\/em>","avg_equity":"1210.50\u4e07","first_date":"2025-07-01","dateline":"2026-02-25","no":27,"company":"\u534e\u6cf0\u671f\u8d27"},{"id":27190,"uid":21618,"user":"\u8054\u70e8\u4f18\u9009","credit":"174.1","equity":"3.17\u4e07","total_nav":"2.1723","max_lost":"15.31%","tn_profit":4570517.580000001,"total_yield":"<em style=\"font-style:normal;color:#ff287e\">117.23%<\/em>","avg_equity":"500.86\u4e07","first_date":"2025-07-01","dateline":"2026-02-25","no":28,"company":"\u94f6\u6cb3\u671f\u8d27"},{"id":26814,"uid":24359,"user":"\u82b1\u82b11","credit":"173.2","equity":"522.06\u4e07","total_nav":"4.6047","max_lost":"22.20%","tn_profit":8246305.469999997,"total_yield":"<em style=\"font-style:normal;color:#ff287e\">360.47%<\/em>","avg_equity":"515.16\u4e07","first_date":"2025-07-01","dateline":"2026-02-25","no":29,"company":"\u6c5f\u6d77\u6c47\u946b"},{"id":26790,"uid":24434,"user":"\u7279\u4e28\u6717\u666e","credit":"172.6","equity":"8906.06\u4e07","total_nav":"2.2949","max_lost":"19.15%","tn_profit":56744806.28,"total_yield":"<em style=\"font-style:normal;color:#ff287e\">129.49%<\/em>","avg_equity":"6429.63\u4e07","first_date":"2025-07-01","dateline":"2026-02-25","no":30,"company":"\u4e2d\u7535\u6295\u5148\u878d"},{"id":27041,"uid":21463,"user":"\u5f90\u738b2","credit":"172.3","equity":"472.02\u4e07","total_nav":"1.4896","max_lost":"6.88%","tn_profit":2400747.3000000003,"total_yield":"<em style=\"font-style:normal;color:#ff287e\">48.96%<\/em>","avg_equity":"779.11\u4e07","first_date":"2025-07-01","dateline":"2026-02-25","no":31,"company":"\u56fd\u8054\u671f\u8d27"},{"id":20941,"uid":20941,"user":"agebar","credit":"171.1","equity":"10","total_nav":"1.7941","max_lost":"12.66%","tn_profit":3268591.03,"total_yield":"<em style=\"font-style:normal;color:#ff287e\">79.41%<\/em>","avg_equity":"493.56\u4e07","first_date":"2025-07-01","dateline":"2026-02-25","no":32,"company":"\u5e7f\u53d1\u671f\u8d27"},{"id":27197,"uid":22189,"user":"yk888999","credit":"170.3","equity":"2358.72\u4e07","total_nav":"1.5882","max_lost":"10.45%","tn_profit":4572410.359999999,"total_yield":"<em style=\"font-style:normal;color:#ff287e\">58.82%<\/em>","avg_equity":"993.57\u4e07","first_date":"2025-07-01","dateline":"2026-02-25","no":33,"company":"\u4e1c\u5434\u671f\u8d27"},{"id":22449,"uid":22020,"user":"\u4e00\u789fxkx","credit":"170.2","equity":"638.83\u4e07","total_nav":"1.5986","max_lost":"9.62%","tn_profit":2392059.15,"total_yield":"<em style=\"font-style:normal;color:#ff287e\">59.86%<\/em>","avg_equity":"523.77\u4e07","first_date":"2025-07-01","dateline":"2026-02-25","no":34,"company":"\u56fd\u6295\u5b89\u4fe1"},{"id":26994,"uid":24359,"user":"302\u65b02","credit":"170.1","equity":"3747.89\u4e07","total_nav":"1.3325","max_lost":"4.02%","tn_profit":6806180.75,"total_yield":"<em style=\"font-style:normal;color:#ff287e\">33.25%<\/em>","avg_equity":"2257.92\u4e07","first_date":"2025-07-01","dateline":"2026-02-25","no":35,"company":"\u4e1c\u5434\u671f\u8d27"},{"id":21699,"uid":21652,"user":"\u6c5f\u6d69","credit":"168.8","equity":"936.23\u4e07","total_nav":"3.8176","max_lost":"22.86%","tn_profit":7303400.480000002,"total_yield":"<em style=\"font-style:normal;color:#ff287e\">281.76%<\/em>","avg_equity":"531.39\u4e07","first_date":"2025-07-01","dateline":"2026-02-25","no":36,"company":"\u4e1c\u8bc1\u671f\u8d27"},{"id":11080,"uid":11080,"user":"\u6c34\u6728\u957f\u91cf-\u5174\u8bc1\u671f\u8d27","credit":"167.3","equity":"2858.90\u4e07","total_nav":"2.8463","max_lost":"22.40%","tn_profit":17286128.779999994,"total_yield":"<em style=\"font-style:normal;color:#ff287e\">184.63%<\/em>","avg_equity":"1689.34\u4e07","first_date":"2025-07-01","dateline":"2026-02-25","no":37,"company":"\u5174\u8bc1\u671f\u8d27"},{"id":25117,"uid":21301,"user":"\u6893\u5f3a\u4e1c\u54342023\u542f\u822a","credit":"167.2","equity":"382.03\u4e07","total_nav":"2.9187","max_lost":"18.91%","tn_profit":2471085.5599999987,"total_yield":"<em style=\"font-style:normal;color:#ff287e\">191.87%<\/em>","avg_equity":"248.80\u4e07","first_date":"2025-07-01","dateline":"2026-02-25","no":38,"company":"\u4e1c\u5434\u671f\u8d27"},{"id":2966,"uid":23840,"user":"\u5e0c\u671b\u5728\u8f6c\u89d21","credit":"166.2","equity":"1687.94\u4e07","total_nav":"3.1115","max_lost":"22.56%","tn_profit":11493645.540000001,"total_yield":"<em style=\"font-style:normal;color:#ff287e\">211.15%<\/em>","avg_equity":"859.93\u4e07","first_date":"2025-07-01","dateline":"2026-02-25","no":39,"company":"\u56fd\u8d38\u671f\u8d27"},{"id":27017,"uid":24362,"user":"\u4ef7\u503c\u5b88\u536b","credit":"165.6","equity":"1166.00\u4e07","total_nav":"2.0685","max_lost":"17.59%","tn_profit":5948668.120000002,"total_yield":"<em style=\"font-style:normal;color:#ff287e\">106.85%<\/em>","avg_equity":"751.76\u4e07","first_date":"2025-07-09","dateline":"2026-02-25","no":40,"company":"\u4e1c\u8bc1\u671f\u8d27"},{"id":24412,"uid":22590,"user":"\u8dec\u6b65\u81f3\u5343\u91cc\u6c38\u5b891\u53f7","credit":"165.2","equity":"3897.78\u4e07","total_nav":"1.5832","max_lost":"13.98%","tn_profit":17683883.729999997,"total_yield":"<em style=\"font-style:normal;color:#ff287e\">58.32%<\/em>","avg_equity":"3638.46\u4e07","first_date":"2025-07-01","dateline":"2026-02-25","no":41,"company":"\u6c38\u5b89\u671f\u8d27"},{"id":17477,"uid":24317,"user":"\u738b\u8863\u8c372018","credit":"164.8","equity":"1080.19\u4e07","total_nav":"1.5588","max_lost":"11.76%","tn_profit":3770755.3699999987,"total_yield":"<em style=\"font-style:normal;color:#ff287e\">55.88%<\/em>","avg_equity":"873.45\u4e07","first_date":"2025-07-01","dateline":"2026-02-25","no":42,"company":"\u8d22\u4fe1\u671f\u8d27"},{"id":24723,"uid":21463,"user":"\u6d3c\u76c8\u5957\u5229\u5341\u4e00\u53f7","credit":"164.7","equity":"5552.43\u4e07","total_nav":"1.2956","max_lost":"4.19%","tn_profit":12702581.160000004,"total_yield":"<em style=\"font-style:normal;color:#ff287e\">29.56%<\/em>","avg_equity":"4824.84\u4e07","first_date":"2025-07-01","dateline":"2026-02-25","no":43,"company":"\u5fbd\u5546\u671f\u8d27"},{"id":4150,"uid":4150,"user":"\u5b81\u6ce2\u91d1\u624b\u5957","credit":"163.9","equity":"16.25\u4e07","total_nav":"2.0132","max_lost":"2.44%","tn_profit":409280.27999999997,"total_yield":"<em style=\"font-style:normal;color:#ff287e\">101.32%<\/em>","avg_equity":"34.32\u4e07","first_date":"2025-07-01","dateline":"2026-02-25","no":44,"company":"\u4e2d\u8f89\u671f\u8d27"},{"id":21292,"uid":23398,"user":"\u6b27\u9633\u5bb9\u51b0","credit":"163.5","equity":"375.12\u4e07","total_nav":"1.5923","max_lost":"12.75%","tn_profit":5286113.92,"total_yield":"<em style=\"font-style:normal;color:#ff287e\">59.23%<\/em>","avg_equity":"739.11\u4e07","first_date":"2025-07-01","dateline":"2026-02-25","no":45,"company":"\u534e\u6cf0\u671f\u8d27"},{"id":24874,"uid":18894,"user":"\u661f\u706b\u4e00\u53f7\uff08\u7eed\uff09","credit":"163.2","equity":"557.75\u4e07","total_nav":"1.3801","max_lost":"6.15%","tn_profit":1674074.23,"total_yield":"<em style=\"font-style:normal;color:#ff287e\">38.01%<\/em>","avg_equity":"495.09\u4e07","first_date":"2025-07-01","dateline":"2026-02-25","no":46,"company":"\u6d77\u8bc1\u671f\u8d27"},{"id":24701,"uid":21463,"user":"\u5c0f\u7b28\u6807\u51c6\u578b","credit":"161.5","equity":"2614.74\u4e07","total_nav":"1.3455","max_lost":"7.92%","tn_profit":5944835.330000003,"total_yield":"<em style=\"font-style:normal;color:#ff287e\">34.55%<\/em>","avg_equity":"2227.67\u4e07","first_date":"2025-07-01","dateline":"2025-12-11","no":47,"company":"\u6210\u90fd\u500d\u7279"},{"id":26953,"uid":22024,"user":"\u66fe5","credit":"161.3","equity":"101.32\u4e07","total_nav":"4.4108","max_lost":"21.79%","tn_profit":2386627.6200000015,"total_yield":"<em style=\"font-style:normal;color:#ff287e\">341.08%<\/em>","avg_equity":"162.95\u4e07","first_date":"2025-07-01","dateline":"2026-02-25","no":48,"company":"\u521b\u5143\u671f\u8d27"},{"id":26794,"uid":23398,"user":"\u7231\u98de\u6d59\u77f3","credit":"161.2","equity":"2184.74","total_nav":"1.5344","max_lost":"13.70%","tn_profit":10232703.109999998,"total_yield":"<em style=\"font-style:normal;color:#ff287e\">53.44%<\/em>","avg_equity":"1835.66\u4e07","first_date":"2025-07-01","dateline":"2026-02-25","no":49,"company":"\u6d59\u77f3\u671f\u8d27"},{"id":26898,"uid":18894,"user":"ZH150","credit":"160.9","equity":"109.18\u4e07","total_nav":"1.7338","max_lost":"11.72%","tn_profit":1111889.2399999998,"total_yield":"<em style=\"font-style:normal;color:#ff287e\">73.38%<\/em>","avg_equity":"180.56\u4e07","first_date":"2025-07-01","dateline":"2026-02-25","no":50,"company":"\u56fd\u76db\u671f\u8d27"}],"field":{"credit":"\u7efc\u5408\u79ef\u5206","equity":"\u6700\u65b0\u6743\u76ca","total_nav":"\u7d2f\u8ba1\u51c0\u503c","max_lost":"\u6700\u5927\u56de\u64a4"}}}