{"response":0,"message":"","data":{"data":[{"uid":8006,"profit":"<em style=\"font-style:normal;color:#ff287e\">100.00\u4ebf<\/em>","avg_profit":145.76,"winning":"50.40","fee":"4586.29\u4e07","dateline":"2021-04-09","first_date":"2014-10-24","equity":1.39,"id":8006,"user":"\u5929\u79be1\u53f7","is_investor":"n","company":"","no":1,"_pid_":8006},{"uid":12965,"profit":"<em style=\"font-style:normal;color:#ff287e\">100.00\u4ebf<\/em>","avg_profit":351.34,"winning":"52.19","fee":"1.88\u4ebf","dateline":"2024-06-06","first_date":"2016-06-14","equity":2382.59,"id":12965,"user":"\u6797\u5ca9","is_investor":"n","company":"","no":2,"_pid_":12965},{"uid":7862,"profit":"<em style=\"font-style:normal;color:#ff287e\">71.16\u4ebf<\/em>","avg_profit":1223.68,"winning":"64.09","fee":"2381.63\u4e07","dateline":"2026-02-25","first_date":"2014-07-21","equity":"346.92\u4e07","id":7862,"user":"\u58c1\u864e\u8d44\u672c","is_investor":"n","company":"","no":3,"_pid_":7862},{"uid":20943,"profit":"<em style=\"font-style:normal;color:#ff287e\">68.30\u4ebf<\/em>","avg_profit":763.75,"winning":"69.65","fee":"4529.02\u4e07","dateline":"2024-06-06","first_date":"2020-01-10","equity":1119.9,"id":20943,"user":"\u70b9\u77f3\u6210\u91d1\u4e2d\u4fe1\u671f\u8d27\u91d1\u74031\u53f7","is_investor":"n","company":"","no":4,"_pid_":20943},{"uid":7217,"profit":"<em style=\"font-style:normal;color:#ff287e\">67.73\u4ebf<\/em>","avg_profit":170.64,"winning":"42.14","fee":"1.18\u4ebf","dateline":"2024-06-06","first_date":"2014-04-28","equity":1001,"id":7217,"user":"xmkyx","is_investor":"n","company":"","no":5,"_pid_":7217},{"uid":20121,"profit":"<em style=\"font-style:normal;color:#ff287e\">64.33\u4ebf<\/em>","avg_profit":690.57,"winning":"78.12","fee":"2480.42\u4e07","dateline":"2026-02-25","first_date":"2019-07-01","equity":"1466.97\u4e07","id":20121,"user":"\u5357\u65b9\u4eba","is_investor":"n","company":"","no":6,"_pid_":20121},{"uid":18939,"profit":"<em style=\"font-style:normal;color:#ff287e\">58.94\u4ebf<\/em>","avg_profit":517.92,"winning":"58.12","fee":"4521.45\u4e07","dateline":"2024-06-06","first_date":"2018-08-27","equity":"856.19\u4e07","id":18939,"user":"\u541b\u7fcaCTA\u8fdb\u53d61\u53f7","is_investor":"n","company":"","no":7,"_pid_":18939},{"uid":16537,"profit":"<em style=\"font-style:normal;color:#ff287e\">51.93\u4ebf<\/em>","avg_profit":244.17,"winning":"61.64","fee":"6959.28\u4e07","dateline":"2025-04-24","first_date":"2017-08-31","equity":"2.67\u4e07","id":16537,"user":"\u4e00\u9897\u661f14\u534e\u5b89\u51e1","is_investor":"n","company":"","no":8,"_pid_":16537},{"uid":19260,"profit":"<em style=\"font-style:normal;color:#ff287e\">47.92\u4ebf<\/em>","avg_profit":182.46,"winning":"67.53","fee":"8521.24\u4e07","dateline":"2026-02-05","first_date":"2019-04-10","equity":"16.36\u4e07","id":19260,"user":"\u8c2dsir\u4e2d\u4fe1","is_investor":"n","company":"","no":9,"_pid_":19260},{"uid":20329,"profit":"<em style=\"font-style:normal;color:#ff287e\">47.75\u4ebf<\/em>","avg_profit":98.71,"winning":"44.82","fee":"1.99\u4ebf","dateline":"2025-11-24","first_date":"2019-10-31","equity":"30.62\u4e07","id":20329,"user":"\u76d8\u524d\u8ba1\u5212\u7eed","is_investor":"n","company":"","no":10,"_pid_":20329},{"uid":6416,"profit":"<em style=\"font-style:normal;color:#ff287e\">42.32\u4ebf<\/em>","avg_profit":47.49,"winning":"57.06","fee":"1.55\u4ebf","dateline":"2025-12-18","first_date":"2013-12-31","equity":"7.01\u4e07","id":6416,"user":"\u4e00\u9897\u661f15\u5fbd\u5546","is_investor":"n","company":"","no":11,"_pid_":6416},{"uid":3935,"profit":"<em style=\"font-style:normal;color:#ff287e\">36.92\u4ebf<\/em>","avg_profit":111.7,"winning":"57.26","fee":"3767.97\u4e07","dateline":"2019-05-28","first_date":"2013-02-22","equity":"4.09\u4e07","id":3935,"user":"\u51ef\u6cfd\u6295\u8d44","is_investor":"n","company":"","no":12,"_pid_":3935},{"uid":20989,"profit":"<em style=\"font-style:normal;color:#ff287e\">29.58\u4ebf<\/em>","avg_profit":235.38,"winning":"50.67","fee":"5565.06\u4e07","dateline":"2023-08-07","first_date":"2020-03-24","equity":66.13,"id":20989,"user":"\u76d8\u524d\u8ba1\u52122","is_investor":"n","company":"","no":13,"_pid_":20989},{"uid":2966,"profit":"<em style=\"font-style:normal;color:#ff287e\">28.51\u4ebf<\/em>","avg_profit":226.32,"winning":"24.10","fee":"2767.92\u4e07","dateline":"2026-02-09","first_date":"2012-09-19","equity":"1687.94\u4e07","id":2966,"user":"\u5e0c\u671b\u5728\u8f6c\u89d21","is_investor":"n","company":"","no":14,"_pid_":2966},{"uid":19813,"profit":"<em style=\"font-style:normal;color:#ff287e\">26.29\u4ebf<\/em>","avg_profit":584.24,"winning":"38.89","fee":"1579.98\u4e07","dateline":"2024-06-06","first_date":"2019-01-28","equity":216.66,"id":19813,"user":"\u9ed1\u732b\u767d\u732b\u91d1\u878d\u5de5\u4f5c\u5ba4","is_investor":"n","company":"","no":15,"_pid_":19813},{"uid":2179,"profit":"<em style=\"font-style:normal;color:#ff287e\">25.91\u4ebf<\/em>","avg_profit":1268.08,"winning":"54.04","fee":"1610.22\u4e07","dateline":"2021-04-07","first_date":"2012-05-18","equity":0,"id":2179,"user":"\u6301\u8d62\u6295\u8d44","is_investor":"n","company":"","no":16,"_pid_":2179},{"uid":8948,"profit":"<em style=\"font-style:normal;color:#ff287e\">24.74\u4ebf<\/em>","avg_profit":865.69,"winning":"52.91","fee":"1344.61\u4e07","dateline":"2023-08-07","first_date":"2014-12-24","equity":0,"id":8948,"user":"\u51e1\u683c\u91d1\u5de5\u4e13\u62371\u53f7","is_investor":"n","company":"","no":17,"_pid_":8948},{"uid":5451,"profit":"<em style=\"font-style:normal;color:#ff287e\">24.37\u4ebf<\/em>","avg_profit":1464.86,"winning":"85.61","fee":"513.33\u4e07","dateline":"2021-04-09","first_date":"2013-09-25","equity":641.54,"id":5451,"user":"\u6295\u8d44\u5728\u7ebf2\u53f7","is_investor":"n","company":"","no":18,"_pid_":5451},{"uid":2124,"profit":"<em style=\"font-style:normal;color:#ff287e\">24.23\u4ebf<\/em>","avg_profit":105.44,"winning":"52.77","fee":"2848.28\u4e07","dateline":"2021-04-06","first_date":"2012-05-14","equity":400,"id":2124,"user":"\u5999\u4e3a\u4e3a\u4e09","is_investor":"n","company":"","no":19,"_pid_":2124},{"uid":12699,"profit":"<em style=\"font-style:normal;color:#ff287e\">23.05\u4ebf<\/em>","avg_profit":42.11,"winning":"41.22","fee":"2.03\u4ebf","dateline":"2025-03-03","first_date":"2016-11-18","equity":"205.49\u4e07","id":12699,"user":"\u671f\u8d27\u5c0f\u8349","is_investor":"n","company":"","no":20,"_pid_":12699},{"uid":17999,"profit":"<em style=\"font-style:normal;color:#ff287e\">22.77\u4ebf<\/em>","avg_profit":255.99,"winning":"54.86","fee":"3553.18\u4e07","dateline":"2025-08-29","first_date":"2018-08-31","equity":769.64,"id":17999,"user":"L","is_investor":"n","company":"","no":21,"_pid_":17999},{"uid":3087,"profit":"<em style=\"font-style:normal;color:#ff287e\">20.60\u4ebf<\/em>","avg_profit":1672.48,"winning":"44.59","fee":"731.56\u4e07","dateline":"2021-04-06","first_date":"2012-10-11","equity":7.92,"id":3087,"user":"\u7f8e\u597d\u6295\u8d44","is_investor":"n","company":"","no":22,"_pid_":3087},{"uid":3879,"profit":"<em style=\"font-style:normal;color:#ff287e\">20.39\u4ebf<\/em>","avg_profit":7546.36,"winning":"100.00","fee":"177.82\u4e07","dateline":"2021-04-09","first_date":"2013-02-18","equity":46.68,"id":3879,"user":"\u5c71\u6cf0\u4e00\u53f7","is_investor":"n","company":"","no":23,"_pid_":3879},{"uid":7033,"profit":"<em style=\"font-style:normal;color:#ff287e\">19.90\u4ebf<\/em>","avg_profit":296.21,"winning":"44.09","fee":"1559.20\u4e07","dateline":"2024-06-06","first_date":"2014-04-08","equity":"6.37\u4e07","id":7033,"user":"\u5728\u8d62\u6295\u8d44-\u7070\u592a\u90ce","is_investor":"n","company":"","no":24,"_pid_":7033},{"uid":20305,"profit":"<em style=\"font-style:normal;color:#ff287e\">19.19\u4ebf<\/em>","avg_profit":271.91,"winning":"45.99","fee":"3042.31\u4e07","dateline":"2024-06-06","first_date":"2019-06-26","equity":"6.61\u4e07","id":20305,"user":"\u5c0f\u519c\u592b","is_investor":"n","company":"","no":25,"_pid_":20305},{"uid":11650,"profit":"<em style=\"font-style:normal;color:#ff287e\">19.04\u4ebf<\/em>","avg_profit":378.34,"winning":"37.49","fee":"1653.75\u4e07","dateline":"2026-02-03","first_date":"2016-01-04","equity":"6625.22\u4e07","id":11650,"user":"\u8001\u706b\u9e21","is_investor":"n","company":"","no":26,"_pid_":11650},{"uid":5062,"profit":"<em style=\"font-style:normal;color:#ff287e\">18.89\u4ebf<\/em>","avg_profit":635.31,"winning":"61.28","fee":"507.88\u4e07","dateline":"2024-06-06","first_date":"2013-12-03","equity":5288.48,"id":5062,"user":"\u5b8f\u6e90\u4e00\u53f7","is_investor":"n","company":"","no":27,"_pid_":5062},{"uid":10098,"profit":"<em style=\"font-style:normal;color:#ff287e\">16.77\u4ebf<\/em>","avg_profit":232.23,"winning":"56.18","fee":"2204.68\u4e07","dateline":"2024-05-14","first_date":"2015-06-01","equity":0,"id":10098,"user":"shhuanghuang","is_investor":"n","company":"","no":28,"_pid_":10098},{"uid":2344,"profit":"<em style=\"font-style:normal;color:#ff287e\">14.99\u4ebf<\/em>","avg_profit":99.82,"winning":"55.49","fee":"2758.70\u4e07","dateline":"2021-04-06","first_date":"2012-06-11","equity":108.96,"id":2344,"user":"\u5999\u4e3aRS001","is_investor":"n","company":"","no":29,"_pid_":2344},{"uid":21611,"profit":"<em style=\"font-style:normal;color:#ff287e\">14.88\u4ebf<\/em>","avg_profit":1648.45,"winning":"54.06","fee":"508.95\u4e07","dateline":"2026-02-02","first_date":"2020-02-18","equity":"121.65\u4e07","id":21611,"user":"\u5fc3\u884c\u8005\u2605\u7537\u4e3b\u89d2\u4e4b\u60e0\u98ce\u548c\u6636","is_investor":"n","company":"","no":30,"_pid_":21611},{"uid":23611,"profit":"<em style=\"font-style:normal;color:#ff287e\">14.30\u4ebf<\/em>","avg_profit":69.35,"winning":"26.33","fee":"8644.61\u4e07","dateline":"2022-05-26","first_date":"2018-02-28","equity":"105.39\u4e07","id":23611,"user":"\u5c0f\u5c0f\u7684\u97ed\u83dc1","is_investor":"n","company":"","no":31,"_pid_":23611},{"uid":18949,"profit":"<em style=\"font-style:normal;color:#ff287e\">14.29\u4ebf<\/em>","avg_profit":130.83,"winning":"53.76","fee":"4451.91\u4e07","dateline":"2025-09-30","first_date":"2018-08-24","equity":"119.20\u4e07","id":18949,"user":"\u91d1\u6bdb\u72ee\u738b","is_investor":"n","company":"","no":32,"_pid_":18949},{"uid":7574,"profit":"<em style=\"font-style:normal;color:#ff287e\">14.22\u4ebf<\/em>","avg_profit":718.38,"winning":"47.93","fee":"674.62\u4e07","dateline":"2024-06-06","first_date":"2014-06-16","equity":2.04,"id":7574,"user":"\u8fa3\u53ef\u4e0d\u4e00\u6837","is_investor":"n","company":"","no":33,"_pid_":7574},{"uid":21447,"profit":"<em style=\"font-style:normal;color:#ff287e\">11.72\u4ebf<\/em>","avg_profit":173.3,"winning":"34.01","fee":"691.95\u4e07","dateline":"2026-02-04","first_date":"2020-07-06","equity":"110.81\u4e07","id":21447,"user":"\u5565\u4e5f\u4e0d\u662f","is_investor":"n","company":"","no":34,"_pid_":21447},{"uid":17713,"profit":"<em style=\"font-style:normal;color:#ff287e\">11.69\u4ebf<\/em>","avg_profit":312.15,"winning":"45.45","fee":"1522.88\u4e07","dateline":"2024-06-06","first_date":"2018-03-02","equity":2780.41,"id":17713,"user":"haihai","is_investor":"n","company":"","no":35,"_pid_":17713},{"uid":6916,"profit":"<em style=\"font-style:normal;color:#ff287e\">11.68\u4ebf<\/em>","avg_profit":320.5,"winning":"58.24","fee":"1262.81\u4e07","dateline":"2026-02-03","first_date":"2014-03-11","equity":"8664.59\u4e07","id":6916,"user":"\u6d6a\u82b1\u4e09\u53f7","is_investor":"n","company":"","no":36,"_pid_":6916},{"uid":11096,"profit":"<em style=\"font-style:normal;color:#ff287e\">11.53\u4ebf<\/em>","avg_profit":147.51,"winning":"33.08","fee":"2475.48\u4e07","dateline":"2024-06-06","first_date":"2016-03-24","equity":1163.6,"id":11096,"user":"tonect","is_investor":"n","company":"","no":37,"_pid_":11096},{"uid":20041,"profit":"<em style=\"font-style:normal;color:#ff287e\">11.49\u4ebf<\/em>","avg_profit":593.7,"winning":"42.49","fee":"903.34\u4e07","dateline":"2026-02-24","first_date":"2019-03-06","equity":"291.78\u4e07","id":20041,"user":"\u5fc3\u884c\u8005&\u4e91\u5728\u9752\u5929\u6c34\u5728\u74f6","is_investor":"n","company":"","no":38,"_pid_":20041},{"uid":19201,"profit":"<em style=\"font-style:normal;color:#ff287e\">11.28\u4ebf<\/em>","avg_profit":925.54,"winning":"46.95","fee":"462.95\u4e07","dateline":"2025-06-30","first_date":"2019-03-04","equity":"25.16\u4e07","id":19201,"user":"\u5609\u661f\u98d2\u9732\u7d2b","is_investor":"n","company":"","no":39,"_pid_":19201},{"uid":13736,"profit":"<em style=\"font-style:normal;color:#ff287e\">11.18\u4ebf<\/em>","avg_profit":413.09,"winning":"56.34","fee":"1030.39\u4e07","dateline":"2025-12-29","first_date":"2016-09-13","equity":"46.76\u4e07","id":13736,"user":"\u59d0\u59d0","is_investor":"n","company":"","no":40,"_pid_":13736},{"uid":5058,"profit":"<em style=\"font-style:normal;color:#ff287e\">10.86\u4ebf<\/em>","avg_profit":138.11,"winning":"44.27","fee":"2287.93\u4e07","dateline":"2026-02-25","first_date":"2013-10-08","equity":"292.29\u4e07","id":5058,"user":"103606141","is_investor":"n","company":"","no":41,"_pid_":5058},{"uid":21268,"profit":"<em style=\"font-style:normal;color:#ff287e\">10.71\u4ebf<\/em>","avg_profit":170.27,"winning":"60.19","fee":"2515.55\u4e07","dateline":"2024-06-06","first_date":"2019-11-29","equity":1835.81,"id":21268,"user":"\u96f6\u70b9\u8bb2\u53f0-\u6c47\u878dzb","is_investor":"n","company":"","no":42,"_pid_":21268},{"uid":19463,"profit":"<em style=\"font-style:normal;color:#ff287e\">10.59\u4ebf<\/em>","avg_profit":4279.49,"winning":"74.60","fee":"96.70\u4e07","dateline":"2024-06-06","first_date":"2018-12-27","equity":504.12,"id":19463,"user":"\u5b59\u8fdc\u5c711","is_investor":"n","company":"","no":43,"_pid_":19463},{"uid":20664,"profit":"<em style=\"font-style:normal;color:#ff287e\">10.49\u4ebf<\/em>","avg_profit":2440.86,"winning":"30.60","fee":"152.97\u4e07","dateline":"2023-08-07","first_date":"2019-11-11","equity":0,"id":20664,"user":"\u6069\u6cfd1\u53f7\u8bc1\u5238\u6295\u8d44\u79c1\u52df\u57fa\u91d1","is_investor":"n","company":"","no":44,"_pid_":20664},{"uid":3353,"profit":"<em style=\"font-style:normal;color:#ff287e\">10.46\u4ebf<\/em>","avg_profit":1293.68,"winning":"51.48","fee":"273.77\u4e07","dateline":"2015-06-02","first_date":"2012-11-29","equity":"3705.95\u4e07","id":3353,"user":"f\u516d\u5e74","is_investor":"n","company":"","no":45,"_pid_":3353},{"uid":5293,"profit":"<em style=\"font-style:normal;color:#ff287e\">10.07\u4ebf<\/em>","avg_profit":37.6,"winning":"59.63","fee":"6104.34\u4e07","dateline":"2026-02-10","first_date":"2013-11-18","equity":"154.47\u4e07","id":5293,"user":"\u56fa\u5229\u8d44\u4ea7\u8d8b\u52bf\u4e3a\u738b","is_investor":"n","company":"","no":46,"_pid_":5293},{"uid":6707,"profit":"<em style=\"font-style:normal;color:#ff287e\">9.89\u4ebf<\/em>","avg_profit":4474.69,"winning":"100.00","fee":"82.95\u4e07","dateline":"2021-04-09","first_date":"2014-02-14","equity":0.63,"id":6707,"user":"\u5584\u6cfd\u6807\u51c6","is_investor":"n","company":"","no":47,"_pid_":6707},{"uid":2617,"profit":"<em style=\"font-style:normal;color:#ff287e\">9.75\u4ebf<\/em>","avg_profit":132.37,"winning":"53.64","fee":"974.22\u4e07","dateline":"2021-04-07","first_date":"2012-07-19","equity":100.68,"id":2617,"user":"\u5999\u4e3a-ZMF","is_investor":"n","company":"","no":48,"_pid_":2617},{"uid":14474,"profit":"<em style=\"font-style:normal;color:#ff287e\">9.66\u4ebf<\/em>","avg_profit":345.99,"winning":"45.46","fee":"1012.58\u4e07","dateline":"2026-02-24","first_date":"2017-04-17","equity":"292.00\u4e07","id":14474,"user":"\u5fc3\u884c\u8005\u2605\u79cb\u971c\u5207\u7389\u5251-\u91d1\u978d\u4e94\u9675\u8c6a","is_investor":"n","company":"","no":49,"_pid_":14474},{"uid":2918,"profit":"<em style=\"font-style:normal;color:#ff287e\">9.30\u4ebf<\/em>","avg_profit":66.95,"winning":"50.67","fee":"2076.47\u4e07","dateline":"2022-07-07","first_date":"2012-09-07","equity":0,"id":2918,"user":"\u53cc\u8d62\u6295\u8d44","is_investor":"n","company":"","no":50,"_pid_":2918}],"pageNav":""}}